_rizin.cpython-312-darwin.so
ak_rz_bindings-0.6.0.data/purelib/rizin.py
ak_rz_bindings.dylibs/librz_magic.0.9.dylib
ak_rz_bindings.dylibs/librz_io.0.9.dylib
ak_rz_bindings.dylibs/librz_type.0.9.dylib
ak_rz_bindings.dylibs/librz_egg.0.9.dylib
ak_rz_bindings.dylibs/librz_diff.0.9.dylib
ak_rz_bindings.dylibs/librz_socket.0.9.dylib
ak_rz_bindings.dylibs/librz_cons.0.9.dylib
ak_rz_bindings.dylibs/librz_debug.0.9.dylib
ak_rz_bindings.dylibs/librz_util.0.9.dylib
ak_rz_bindings.dylibs/librz_lang.0.9.dylib
ak_rz_bindings.dylibs/librz_search.0.9.dylib
ak_rz_bindings.dylibs/librz_bin.0.9.dylib
ak_rz_bindings.dylibs/librz_arch.0.9.dylib
ak_rz_bindings.dylibs/librz_syscall.0.9.dylib
ak_rz_bindings.dylibs/librz_core.0.9.dylib
ak_rz_bindings.dylibs/librz_hash.0.9.dylib
ak_rz_bindings.dylibs/librz_flag.0.9.dylib
ak_rz_bindings.dylibs/librz_crypto.0.9.dylib
ak_rz_bindings.dylibs/librz_il.0.9.dylib
ak_rz_bindings.dylibs/librz_config.0.9.dylib
ak_rz_bindings.dylibs/librz_demangler.0.9.dylib
ak_rz_bindings.dylibs/librz_reg.0.9.dylib
ak_rz_bindings.dylibs/librz_sign.0.9.dylib
ak_rz_bindings-0.6.0.dist-info/RECORD
ak_rz_bindings-0.6.0.dist-info/WHEEL
ak_rz_bindings-0.6.0.dist-info/METADATA
