Metadata-Version: 2.1
Name: ak-rz-bindings
Version: 0.6.0
Requires-Python: >=3.9
